loop/__init__.py
loop/agent/__init__.py
loop/agent/client.py
loop/agent/hooks.py
loop/cli/__init__.py
loop/cli/commands.py
loop/cli/main.py
loop/cli/ui.py
loop/core/__init__.py
loop/core/config.py
loop/core/errors.py
loop/core/ralph_loop.py
loop/core/session.py
assiworks_loop-0.3.0.dist-info/METADATA
assiworks_loop-0.3.0.dist-info/WHEEL
assiworks_loop-0.3.0.dist-info/entry_points.txt
assiworks_loop-0.3.0.dist-info/top_level.txt
assiworks_loop-0.3.0.dist-info/RECORD
